pystreamgraph/__init__.py
pystreamgraph/py.typed
pystreamgraph-0.1.4.dist-info/METADATA
pystreamgraph-0.1.4.dist-info/WHEEL
pystreamgraph-0.1.4.dist-info/licenses/LICENSE
pystreamgraph-0.1.4.dist-info/RECORD
