Metadata-Version: 2.4
Name: pystreamgraph
Version: 0.1.4
Summary: A compact Matplotlib streamgraph helper with ordering, margins, smoothing, curves, and labels.
Project-URL: Homepage, https://github.com/MNoichl/pystreamgraph
Project-URL: Issues, https://github.com/MNoichl/pystreamgraph/issues
Project-URL: Documentation, https://MNoichl.github.io/pystreamgraph/
Author: Rapty
License: MIT License
License-File: LICENSE
Keywords: charts,matplotlib,plot,streamgraph,visualization
Classifier: Development Status :: 4 - Beta
Classifier: Intended Audience :: Developers
Classifier: Intended Audience :: Science/Research
Classifier: License :: OSI Approved :: MIT License
Classifier: Programming Language :: Python
Classifier: Programming Language :: Python :: 3
Classifier: Programming Language :: Python :: 3 :: Only
Classifier: Programming Language :: Python :: 3.8
Classifier: Programming Language :: Python :: 3.9
Classifier: Programming Language :: Python :: 3.10
Classifier: Programming Language :: Python :: 3.11
Classifier: Programming Language :: Python :: 3.12
Classifier: Topic :: Scientific/Engineering :: Visualization
Classifier: Typing :: Typed
Requires-Python: >=3.8
Requires-Dist: matplotlib>=3.4
Requires-Dist: numpy>=1.20
Requires-Dist: scipy>=1.6; python_version >= '3.8'
